<package version="0.0">
  <name>com.livecode.widget.navrad</name>
  <title>Navigation RAD</title>
  <author>LiveCode</author>
  <version>2.0.0</version>
  <license>community</license>
  <type>widget</type>
  <requires name="com.livecode.canvas"/>
  <requires name="com.livecode.library.iconsvg"/>
  <requires name="com.livecode.library.widgetutils"/>
  <requires name="com.livecode.array"/>
  <requires name="com.livecode.list"/>
  <requires name="com.livecode.arithmetic"/>
  <requires name="com.livecode.logic"/>
  <requires name="com.livecode.widget"/>
  <requires name="com.livecode.binary"/>
  <requires name="com.livecode.string"/>
  <requires name="com.livecode.type"/>
  <requires name="com.livecode.char"/>
  <requires name="com.livecode.engine"/>
  <requires name="com.livecode.mathfoundation"/>
  <requires name="com.livecode.sort"/>
  <requires name="com.livecode.typeconvert"/>
  <requires name="com.livecode.byte"/>
  <metadata key="preferredSize">320,49</metadata>
  <metadata key="svgicon">M3,4.2v29.5h80.2V4.2H3z M14.8,11.5c1-0.2,2.5-0.3,3.8-0.3c2.1,0,3.5,0.4,4.5,1.3c0.8,0.7,1.2,1.7,1.2,2.9	c0,2-1.3,3.4-2.9,4v0.1c1.2,0.4,1.9,1.5,2.3,3.1c0.5,2.2,0.9,3.7,1.2,4.3h-2.1c-0.3-0.4-0.6-1.8-1-3.7c-0.5-2.1-1.3-2.9-3.1-3h-1.9v6.7h-2V11.5z M16.8,18.6h2c2.1,0,3.5-1.2,3.5-2.9c0-2-1.4-2.9-3.6-2.9c-1,0-1.7,0.1-2,0.2V18.6z M39.5,22l-1.6,4.9h-2.1l5.3-15.5	h2.4l5.3,15.5h-2.1L45,22H39.5z M44.6,20.4L43,15.9c-0.3-1-0.6-1.9-0.8-2.8h0C42,14,41.7,15,41.4,15.9l-1.5,4.5H44.6z M60.8,11.5c1.2-0.2,2.7-0.3,4.3-0.3c2.9,0,4.9,0.7,6.3,1.9c1.4,1.3,2.2,3.1,2.2,5.6c0,2.5-0.8,4.6-2.2,6c-1.4,1.4-3.8,2.2-6.9,2.2	c-1.4,0-2.6-0.1-3.6-0.2V11.5z M62.8,25.2c0.5,0.1,1.2,0.1,2,0.1c4.3,0,6.6-2.4,6.6-6.6c0-3.7-2-6-6.3-6c-1,0-1.8,0.1-2.3,0.2V25.2z</metadata>
  <metadata key="hiliteColor.editor">com.livecode.pi.color</metadata>
  <metadata key="hiliteColor.label">Selected item color</metadata>
  <metadata key="hiliteColor.section">Colors</metadata>
  <metadata key="hiliteColor.default">10,95,244</metadata>
  <metadata key="foregroundColor.editor">com.livecode.pi.color</metadata>
  <metadata key="foregroundColor.label">Item color</metadata>
  <metadata key="foregroundColor.section">Colors</metadata>
  <metadata key="foregroundColor.default">128,128,128</metadata>
  <metadata key="backgroundColor.editor">com.livecode.pi.color</metadata>
  <metadata key="backgroundColor.label">Background color</metadata>
  <metadata key="backgroundColor.section">Colors</metadata>
  <metadata key="backgroundColor.default">244,244,244</metadata>
  <metadata key="borderColor.editor">com.livecode.pi.color</metadata>
  <metadata key="borderColor.label">Border color</metadata>
  <metadata key="borderColor.section">Colors</metadata>
  <metadata key="borderColor.default">166,166,166</metadata>
  <property name="itemArray" get="array" set="array"/>
  <metadata key="itemArray.editor">com.livecode.pi.navbar</metadata>
  <metadata key="itemArray.label">Navigation data</metadata>
  <property name="itemNames" get="string" set="string"/>
  <metadata key="itemNames.editor">com.livecode.pi.editorList</metadata>
  <metadata key="itemNames.subeditor">com.livecode.pi.string</metadata>
  <metadata key="itemNames.delimiter">,</metadata>
  <metadata key="itemNames.label">Navigation names</metadata>
  <property name="itemIcons" get="string" set="string"/>
  <metadata key="itemIcons.user_visible">false</metadata>
  <property name="hilitedItemIcons" get="string" set="string"/>
  <metadata key="hilitedItemIcons.user_visible">false</metadata>
  <property name="itemLabels" get="string" set="string"/>
  <metadata key="itemLabels.user_visible">false</metadata>
  <property name="itemStyle" get="string" set="string"/>
  <metadata key="itemStyle.editor">com.livecode.pi.enum</metadata>
  <metadata key="itemStyle.options">icons,text,both</metadata>
  <metadata key="itemStyle.default">both</metadata>
  <metadata key="itemStyle.label">Display style</metadata>
  <property name="hilitedItem" get="integer" set="integer"/>
  <metadata key="hilitedItem.editor">com.livecode.pi.integer</metadata>
  <metadata key="hilitedItem.default">1</metadata>
  <metadata key="hilitedItem.label">Selected item index</metadata>
  <metadata key="hilitedItem.step">1</metadata>
  <metadata key="hilitedItem.min">0</metadata>
  <property name="hilitedItemName" get="string" set="string"/>
  <metadata key="hilitedItemName.label">Selected item name</metadata>
  <property name="preHilitedItem" get="integer" set="string"/>
  <property name="preHilitedItemName" get="string" set="string"/>
  <property name="editMode" get="boolean" set="boolean"/>
  <metadata key="editMode.user_visible">false</metadata>
  <property name="desiredHeight" get="number"/>
  <metadata key="desiredHeight.user_visible">false</metadata>
  <property name="showBorder" get="boolean" set="boolean"/>
  <metadata key="showBorder.default">true</metadata>
  <metadata key="showBorder.label">Show border</metadata>
  <property name="iconFill" get="boolean" set="boolean"/>
  <metadata key="iconFill.default">false</metadata>
  <metadata key="iconFill.label">Icon Fill</metadata>
  <property name="autoRADHilite" get="boolean" set="boolean"/>
  <metadata key="autoRADHilite.default">true</metadata>
  <metadata key="autoRADHilite.label">Auto Hilite</metadata>
  <property name="opaque" get="boolean" set="boolean"/>
  <metadata key="opaque.default">true</metadata>
  <metadata key="opaque.label">Opaque background</metadata>
  <metadata key="textSize.default">10</metadata>
  <handler name="OnSave" parameters="out array" return="any"/>
  <handler name="OnLoad" parameters="in array" return="any"/>
  <handler name="OnCreate" parameters="" return="nothing"/>
  <handler name="OnPaint" parameters="" return="nothing"/>
  <handler name="OnMouseUp" parameters="" return="nothing"/>
  <handler name="OnMouseDown" parameters="" return="nothing"/>
  <handler name="OnMouseMove" parameters="" return="nothing"/>
  <handler name="OnGeometryChanged" parameters="" return="any"/>
  <handler name="iconSelected" parameters="in optional any,in string,in number" return="any"/>
  <handler name="setHiliteColor" parameters="in string" return="nothing"/>
  <handler name="getHiliteColor" parameters="" return="string"/>
  <handler name="getPath" parameters="in string" return="Path"/>
  <handler name="getPaint" parameters="in any,in any" return="Paint"/>
  <handler name="setNavSelectedItem" parameters="in integer" return="nothing"/>
  <handler name="getPreNavSelectedItemName" parameters="" return="string"/>
  <handler name="setPreNavSelectedItemName" parameters="in string" return="nothing"/>
  <handler name="getPreNavSelectedItem" parameters="" return="integer"/>
  <handler name="setPreNavSelectedItem" parameters="in string" return="nothing"/>
  <handler name="setNavSelectedItemName" parameters="in string" return="nothing"/>
  <handler name="getNavSelectedItemName" parameters="" return="string"/>
  <handler name="setItemStyle" parameters="in string" return="nothing"/>
  <handler name="setEditMode" parameters="in boolean" return="nothing"/>
  <handler name="initialiseEditData" parameters="" return="any"/>
  <handler name="setEditableRect" parameters="in string,in number,in Rectangle,in string,in string,in PopupCallback" return="any"/>
  <handler name="setEditableTextRect" parameters="in string,in number,in Rectangle,in string" return="any"/>
  <handler name="setActionRect" parameters="in string,in number,in Rectangle,in string,in ActionCallback,in boolean" return="any"/>
  <handler name="drawEditableRects" parameters="in Canvas" return="any"/>
</package>